algokit_client_generator/__init__.py
algokit_client_generator/__main__.py
algokit_client_generator/cli.py
algokit_client_generator/context.py
algokit_client_generator/document.py
algokit_client_generator/generator.py
algokit_client_generator/generators/__init__.py
algokit_client_generator/generators/app_spec.py
algokit_client_generator/generators/composer.py
algokit_client_generator/generators/header_comments.py
algokit_client_generator/generators/helpers.py
algokit_client_generator/generators/imports.py
algokit_client_generator/generators/typed_client.py
algokit_client_generator/generators/typed_factory.py
algokit_client_generator/py.typed
algokit_client_generator/spec.py
algokit_client_generator/utils.py
algokit_client_generator/writer.py
algokit_client_generator-2.2.0.dist-info/LICENSE
algokit_client_generator-2.2.0.dist-info/METADATA
algokit_client_generator-2.2.0.dist-info/WHEEL
algokit_client_generator-2.2.0.dist-info/entry_points.txt
algokit_client_generator-2.2.0.dist-info/RECORD
