Metadata-Version: 2.3
Name: algokit-client-generator
Version: 2.2.0
Summary: Algorand typed client Generator
License: MIT
Author: Algorand Foundation
Author-email: contact@algorand.foundation
Requires-Python: >=3.10,<4.0
Classifier: License :: OSI Approved :: MIT License
Classifier: Programming Language :: Python :: 3
Classifier: Programming Language :: Python :: 3.10
Classifier: Programming Language :: Python :: 3.11
Classifier: Programming Language :: Python :: 3.12
Classifier: Programming Language :: Python :: 3.13
Requires-Dist: algokit-utils (>=4.0.1,<5.0.0)
